pre_ml-1.0.1.dist-info/DESCRIPTION.rst
pre_ml-1.0.1.dist-info/METADATA
pre_ml-1.0.1.dist-info/RECORD
pre_ml-1.0.1.dist-info/WHEEL
pre_ml-1.0.1.dist-info/metadata.json
pre_ml-1.0.1.dist-info/top_level.txt
preml/__init__.py
preml/__main__.py
preml/feature_select/__init__.py
preml/feature_select/baco.py
preml/feature_select/heuristics.py
preml/io/__init__.py
preml/io/portie.py
preml/showtime/__init__.py
preml/showtime/baco_show.py
preml/showtime/showie.py
